{
  "iteration": "6",
  "hypothesis_id": "H27",
  "timestamp": "2026-02-25T04:00:00Z",
  "task_name": "\u62bd\u51fa\u5019\u88dc\u306b\u5bfe\u3059\u308b\u30b2\u30fc\u30b8\u5bfe\u79f0\u6027\u30fb\u7269\u7406\u7684\u5236\u7d04\u306b\u3088\u308b\u30d5\u30a3\u30eb\u30bf\u30ea\u30f3\u30b0\u3068 FPR \u8a55\u4fa1",
  "computed_values": {
    "tsi_threshold": 10,
    "total_candidates": 5110,
    "filtered_count": 70,
    "pop_amphicheiral_fraction": 0.006017125665355242,
    "sample_amphicheiral_fraction": 0.016408813877168308,
    "enrichment_ratio": 2.7270186447401636,
    "final_top_10": [
      {
        "name": "12a_4",
        "tsi": 24.0,
        "n": 12.0,
        "u": 2.0,
        "s": 0.0,
        "symmetry": "negative amphicheiral",
        "volume": 18.0,
        "is_link": false
      },
      {
        "name": "12a_125",
        "tsi": 24.0,
        "n": 12.0,
        "u": 2.0,
        "s": 0.0,
        "symmetry": "negative amphicheiral",
        "volume": 17.0,
        "is_link": false
      },
      {
        "name": "12a_268",
        "tsi": 24.0,
        "n": 12.0,
        "u": 2.0,
        "s": 0.0,
        "symmetry": "negative amphicheiral",
        "volume": 20.0,
        "is_link": false
      },
      {
        "name": "12a_273",
        "tsi": 24.0,
        "n": 12.0,
        "u": 2.0,
        "s": 0.0,
        "symmetry": "negative amphicheiral",
        "volume": 18.0,
        "is_link": false
      },
      {
        "name": "12a_341",
        "tsi": 24.0,
        "n": 12.0,
        "u": 2.0,
        "s": 0.0,
        "symmetry": "negative amphicheiral",
        "volume": 19.0,
        "is_link": false
      },
      {
        "name": "12a_427",
        "tsi": 24.0,
        "n": 12.0,
        "u": 2.0,
        "s": 0.0,
        "symmetry": "positive amphicheiral",
        "volume": 19.0,
        "is_link": false
      },
      {
        "name": "12a_435",
        "tsi": 24.0,
        "n": 12.0,
        "u": 2.0,
        "s": 0.0,
        "symmetry": "fully amphicheiral",
        "volume": 18.0,
        "is_link": false
      },
      {
        "name": "12a_458",
        "tsi": 24.0,
        "n": 12.0,
        "u": 2.0,
        "s": 0.0,
        "symmetry": "negative amphicheiral",
        "volume": 20.0,
        "is_link": false
      },
      {
        "name": "12a_462",
        "tsi": 24.0,
        "n": 12.0,
        "u": 2.0,
        "s": 0.0,
        "symmetry": "negative amphicheiral",
        "volume": 16.0,
        "is_link": false
      },
      {
        "name": "12a_465",
        "tsi": 24.0,
        "n": 12.0,
        "u": 2.0,
        "s": 0.0,
        "symmetry": "negative amphicheiral",
        "volume": 19.0,
        "is_link": false
      }
    ]
  },
  "ssot_compliance": {
    "all_constants_from_ssot": true,
    "hardcoded_values_found": false,
    "synthetic_data_used": false
  }
}