{
  "iteration": "6",
  "hypothesis_id": "H16",
  "timestamp": "2026-02-23T11:02:51Z",
  "task_name": "Consistency check of kappa with SSoT constants and theoretical refinement",
  "data_sources": {
    "description": "SSoT v7.0 mathematical and physical constants",
    "loaded_via_ssot": true
  },
  "computed_values": {
    "kappa_match": {
      "theory": 0.1308996938995747,
      "ssot": 0.1308996938995747,
      "diff": 0.0
    },
    "alpha_em_inv": {
      "theory": 137.50987083139756,
      "ssot": 137.5098708314,
      "error_pct": 1.7775211308369916e-12
    },
    "sin2theta_w_geometric": {
      "theory": 0.2320136665346545,
      "ssot": 0.23198,
      "error_pct": 0.014510582569270462
    },
    "G_catalan": {
      "theory": 0.916297857297023,
      "ssot": 0.915965594177219,
      "error_pct": 0.036261475147839284
    },
    "alpha_s_kappa_correlation": {
      "alpha_s_ssot": 0.118,
      "kappa_theory": 0.1308996938995747,
      "error_pct": 9.854640232750477
    }
  },
  "theoretical_refinement": {
    "pachner_resonance": "24 * kappa = pi (Half-cycle phase flip resonance)",
    "leech_lattice_link": "24 is the dimensionality of the Leech lattice, the unique even unimodular lattice in D=24.",
    "cft_casimir_energy": "kappa = pi/24 is the vacuum energy density coefficient in 2D CFT (Central charge c=1).",
    "discrete_tqft": "Spacetime update follows a Z_24 cyclic group structure."
  },
  "ssot_compliance": {
    "all_constants_from_ssot": true,
    "hardcoded_values_found": false
  },
  "reproducibility": {
    "computation_time_sec": 0.00029659271240234375
  }
}